MANIFEST.in
README.rst
setup.py
django_webcache.egg-info/PKG-INFO
django_webcache.egg-info/SOURCES.txt
django_webcache.egg-info/dependency_links.txt
django_webcache.egg-info/top_level.txt
webcache/Urllib2BaseHandlers.py
webcache/__init__.py
webcache/admin.py
webcache/models.py
webcache/settings.py
webcache/tests.py
webcache/urlopen.py
webcache/urls.py