Metadata-Version: 1.1
Name: django-webcache
Version: 0.1
Summary: A django web caching app that supports throttling, expiration and compression.
Home-page: https://github.com/dcthomson/django-webcache
Author: Drew Thomson
Author-email: drooby@gmail.com
License: MIT License
Platform: UNKNOWN
Classifier: Environment :: Web Environment
Classifier: Framework :: Django
Classifier: Intended Audience :: Developers
Classifier: License :: OSI Approved :: MIT License
Classifier: Operating System :: OS Independent
Classifier: Programming Language :: Python
Classifier: Programming Language :: Python :: 2
Classifier: Programming Language :: Python :: 2.7
Classifier: Topic :: Internet :: WWW/HTTP
Classifier: Topic :: Internet :: WWW/HTTP :: Dynamic Content
